{
  "project_info": {
    "project_number": "228455590136",
    "project_id": "bongolava-guide-ia-v2",
    "storage_bucket": "bongolava-guide-ia-v2.firebasestorage.app"
  },
  "client": [
    {
      "client_info": {
        "mobilesdk_app_id": "1:228455590136:android:40a5aff636bcd4c35ff30d",
        "android_client_info": {
          "package_name": "com.example.bongolava_ai"
        }
      },
      "oauth_client": [],
      "api_key": [
        {
          "current_key": "AIzaSyAHnkHQnNOaOkjGMXqQDXZT7cYu6hdmXk0"
        }
      ],
      "services": {
        "appinvite_service": {
          "other_platform_oauth_client": []
        }
      }
    }
  ],
  "configuration_version": "1"
}